deepseek_r1_local/__init__.py
deepseek_r1_local/app.py
deepseek_r1_local/cli.py
deepseek_r1_local/templates/index.html
deepseek_r1_local-1.0.0.dist-info/licenses/LICENSE
deepseek_r1_local-1.0.0.dist-info/METADATA
deepseek_r1_local-1.0.0.dist-info/WHEEL
deepseek_r1_local-1.0.0.dist-info/entry_points.txt
deepseek_r1_local-1.0.0.dist-info/top_level.txt
deepseek_r1_local-1.0.0.dist-info/RECORD
