Metadata-Version: 2.4
Name: deepseek-r1-local
Version: 1.0.0
Summary: Offline AI Web UI with Council Deliberation System
Home-page: https://github.com/yourusername/deepseek-r1-local
Author: DeepSeek R1 Local Team
Author-email: contact@example.com
License: MIT
Project-URL: Homepage, https://github.com/yourusername/deepseek-r1-local
Project-URL: Documentation, https://github.com/yourusername/deepseek-r1-local#readme
Project-URL: Repository, https://github.com/yourusername/deepseek-r1-local.git
Project-URL: Bug Tracker, https://github.com/yourusername/deepseek-r1-local/issues
Keywords: ai,deepseek,llm,web-ui,council,local
Classifier: Development Status :: 4 - Beta
Classifier: Intended Audience :: Developers
Classifier: Topic :: Scientific/Engineering :: Artificial Intelligence
Classifier: License :: OSI Approved :: MIT License
Classifier: Programming Language :: Python :: 3
Classifier: Programming Language :: Python :: 3.9
Classifier: Programming Language :: Python :: 3.10
Classifier: Programming Language :: Python :: 3.11
Requires-Python: >=3.9
License-File: LICENSE
Requires-Dist: flask>=3.0.0
Requires-Dist: flask-cors>=4.0.0
Requires-Dist: torch>=2.1.0
Requires-Dist: transformers>=4.36.0
Requires-Dist: requests>=2.31.0
Requires-Dist: beautifulsoup4>=4.12.2
Requires-Dist: duckduckgo-search>=4.0.0
Provides-Extra: dev
Requires-Dist: pytest>=7.0.0; extra == "dev"
Requires-Dist: black>=23.0.0; extra == "dev"
Requires-Dist: flake8>=6.0.0; extra == "dev"
Dynamic: author-email
Dynamic: home-page
Dynamic: license-file
Dynamic: requires-python
